testgen.py
testgen-0.3.dist-info/METADATA
testgen-0.3.dist-info/WHEEL
testgen-0.3.dist-info/top_level.txt
testgen-0.3.dist-info/RECORD
