Metadata-Version: 2.1
Name: testgen
Version: 0.3
Summary: Generate random reproducible competitive programming tests
Home-page: https://github.com/RealA10N/testgen
Author: Alon Krymgand
License: UNKNOWN
Platform: UNKNOWN
Requires-Dist: rich (<11.0,>=10.0)
Requires-Dist: toml (<1.0,>=0.10)
